reto/__init__.py
reto/__main__.py
reto/dependency_graph.py
reto/exceptions.py
reto/sheet.py
reto/start_task.py
reto/task.py
reto/ticks.py
reto/value_task.py
reto-0.1.2.dist-info/LICENSE
reto-0.1.2.dist-info/WHEEL
reto-0.1.2.dist-info/METADATA
reto-0.1.2.dist-info/RECORD
